{
  "setup": {
    "bestProblemSolution": "SolutionCost {cost: -279, solutionKnapsack: {currentKnapsackWeight: 134, knapsackCapacity: 138, knapsackWeights: [12, 16, 4, 2, 11, 14, 2, 15, 6, 2, 8, 2, 14, 16, 11, 14, 10, 0, 20, 14, 1, 3, 17, 11, 2, 16, 6, 19, 9, 20, 14, 17, 2, 14, 11, 17, 3, 14, 10, 15], solution: {size: 15, elements: [32, 1, 33, 34, 3, 36, 7, 9, 11, 15, 19, 21, 22, 24, 31]}}}",
    "methodVariation": "NONE",
    "instance": "../instances/kqbf/kqbf040",
    "numberOfIterations": "1000",
    "targetValue": -275,
    "runningTime": 0.003,
    "numberOfRepetitions": 50,
    "tenureRatio": "0.4",
    "localSearch": "BEST_IMPROVING"
  },
  "time": [
    0.045,
    0.572,
    0.383,
    0.004,
    0.606,
    0.005,
    0.527,
    0.486,
    0.006,
    0.034,
    0.417,
    0.332,
    0.003,
    0.005,
    0.666,
    0.323,
    0.217,
    0.557,
    0.008,
    0.431,
    0.029,
    0.333,
    0.03,
    0.007,
    0.669,
    0.029,
    0.626,
    0.029,
    0.003,
    0.003,
    0.313,
    0.703,
    0.632,
    0.004,
    0.536,
    0.616,
    0.326,
    0.647,
    0.309,
    0.717,
    0.029,
    0.669,
    0.003,
    0.503,
    0.307,
    0.197,
    0.446,
    0.003,
    0.597,
    0.003
  ]
}